slprint/__init__.py
slprint/slowprint.py
slprint11_pkg-1.1.dist-info/LICENSE
slprint11_pkg-1.1.dist-info/METADATA
slprint11_pkg-1.1.dist-info/WHEEL
slprint11_pkg-1.1.dist-info/top_level.txt
slprint11_pkg-1.1.dist-info/RECORD
