Metadata-Version: 2.1
Name: slprint11-pkg
Version: 1.1
Summary: Simple module to display a text with a time interval between each characters.
Home-page: https://github.com/RonaldoVasques/slowprint
Author: Ronaldo Augusto Vasques de Souza
Author-email: vasquessouza.75@gmail.com
License: UNKNOWN
Platform: UNKNOWN
Classifier: Programming Language :: Python :: 3
Classifier: License :: OSI Approved :: MIT License
Classifier: Environment :: Console
Classifier: Development Status :: 5 - Production/Stable
Classifier: Intended Audience :: Developers
Classifier: Operating System :: Microsoft :: Windows :: Windows 10
Classifier: Operating System :: MacOS
Classifier: Operating System :: POSIX
Classifier: Topic :: Terminals
Classifier: Topic :: System :: Shells
Classifier: Topic :: Software Development :: Libraries
Classifier: Topic :: Desktop Environment
Requires-Python: >=3.0
